agt_arena/__init__.py
agt_arena/arena/__init__.py
agt_arena/arena/go_arena.py
agt_arena/arena/rps_arena.py
agt_arena/bots/__init__.py
agt_arena/bots/go_bot.py
agt_arena/bots/rps_bot.py
agt_arena/bots/server/__init__.py
agt_arena/bots/server/bot_server.py
agt_arena/bots/server/go_bot_server.py
agt_arena/bots/server/rps_bot_server.py
agt_arena/game/__init__.py
agt_arena/game/base_game.py
agt_arena/game/dlgo_go/__init__.py
agt_arena/game/dlgo_go/board.py
agt_arena/game/dlgo_go/go_game.py
agt_arena/game/dlgo_go/gotypes.py
agt_arena/game/dlgo_go/scoring.py
agt_arena/game/dlgo_go/utils.py
agt_arena/game/dlgo_go/zobrist.py
agt_arena/game/go/__init__.py
agt_arena/game/go/adversarial_search_problem.py
agt_arena/game/go/go_search_problem.py
agt_arena/game/go/go_utils.py
agt_arena/matchmaker/__init__.py
agt_arena/matchmaker/base_matchmaker.py
agt_arena/matchmaker/elo.py
agt_arena/matchmaker/round_robin.py
cs410_arena/__init__.py
cs410_arena/arena/__init__.py
cs410_arena/arena/go_arena.py
cs410_arena/bots/__init__.py
cs410_arena/bots/go_bot.py
cs410_arena/bots/server/__init__.py
cs410_arena/bots/server/bot_server.py
cs410_arena/game/__init__.py
cs410_arena/game/base_game.py
cs410_arena/game/dlgo_go/__init__.py
cs410_arena/game/dlgo_go/board.py
cs410_arena/game/dlgo_go/go_game.py
cs410_arena/game/dlgo_go/gotypes.py
cs410_arena/game/dlgo_go/scoring.py
cs410_arena/game/dlgo_go/utils.py
cs410_arena/game/dlgo_go/zobrist.py
cs410_arena/game/go/__init__.py
cs410_arena/game/go/adversarial_search_problem.py
cs410_arena/game/go/go_search_problem.py
cs410_arena/game/go/go_utils.py
cs410_arena/matchmaker/__init__.py
cs410_arena/matchmaker/base_matchmaker.py
cs410_arena/matchmaker/elo.py
cs410_arena/matchmaker/round_robin.py
agt_arena-1.6.19.dist-info/METADATA
agt_arena-1.6.19.dist-info/WHEEL
agt_arena-1.6.19.dist-info/top_level.txt
agt_arena-1.6.19.dist-info/RECORD
