Metadata-Version: 2.1
Name: agt-arena
Version: 1.6.19
Summary: The AGT Docker Arena is a dockerized python platform designed to run and implement game environments that autonomous agents can connect to and compete in.
Home-page: UNKNOWN
Author: John Wu
Author-email: john_w_wu@brown.edu
License: UNKNOWN
Platform: UNKNOWN
Requires-Python: >=3.10
Requires-Dist: setuptools
Requires-Dist: numpy >=1.26.3
Requires-Dist: pandas
Requires-Dist: matplotlib
Requires-Dist: tqdm
Requires-Dist: pygame
Requires-Dist: docker
Requires-Dist: flask >=2.0.0
Requires-Dist: requests >=2.25.1
Requires-Dist: agt-server
